README.md
setup.py
tortoises/__init__.py
tortoises/hupu.py
tortoises/parser.py
tortoises.egg-info/PKG-INFO
tortoises.egg-info/SOURCES.txt
tortoises.egg-info/dependency_links.txt
tortoises.egg-info/requires.txt
tortoises.egg-info/top_level.txt
tortoises/mobile/__init__.py
tortoises/scholar/__init__.py
tortoises/scholar/google.py
tortoises/scholar/scihub.py
tortoises/scholar/wos.py
tortoises/util/__init__.py
tortoises/util/help.py
tortoises/util/logger.py
tortoises/util/mul_thread.py
tortoises/web/__init__.py
tortoises/web/agent.py
tortoises/web/driver.py